containerregistry/__init__.py
containerregistry/client/__init__.py
containerregistry/client/docker_creds_.py
containerregistry/client/docker_name_.py
containerregistry/client/monitor_.py
containerregistry/client/v1/__init__.py
containerregistry/client/v1/docker_creds_.py
containerregistry/client/v1/docker_http_.py
containerregistry/client/v1/docker_image_.py
containerregistry/client/v1/docker_session_.py
containerregistry/client/v1/save_.py
containerregistry/client/v2/__init__.py
containerregistry/client/v2/append_.py
containerregistry/client/v2/docker_creds_.py
containerregistry/client/v2/docker_digest_.py
containerregistry/client/v2/docker_http_.py
containerregistry/client/v2/docker_image_.py
containerregistry/client/v2/docker_session_.py
containerregistry/client/v2/util_.py
containerregistry/client/v2/v1_compat_.py
containerregistry/client/v2_2/__init__.py
containerregistry/client/v2_2/append_.py
containerregistry/client/v2_2/docker_creds_.py
containerregistry/client/v2_2/docker_digest_.py
containerregistry/client/v2_2/docker_http_.py
containerregistry/client/v2_2/docker_image_.py
containerregistry/client/v2_2/docker_image_list_.py
containerregistry/client/v2_2/docker_session_.py
containerregistry/client/v2_2/oci_compat_.py
containerregistry/client/v2_2/save_.py
containerregistry/client/v2_2/v2_compat_.py
containerregistry/tools/__init__.py
containerregistry/tools/docker_appender_.py
containerregistry/tools/docker_puller_.py
containerregistry/tools/docker_pusher_.py
containerregistry/tools/fast_flatten_.py
containerregistry/tools/fast_importer_.py
containerregistry/tools/fast_puller_.py
containerregistry/tools/fast_pusher_.py
containerregistry/tools/image_digester_.py
containerregistry/tools/logging_setup_.py
containerregistry/tools/patched_.py
containerregistry/tools/platform_args_.py
containerregistry/transform/__init__.py
containerregistry/transform/v1/__init__.py
containerregistry/transform/v1/metadata_.py
containerregistry/transform/v2_2/__init__.py
containerregistry_ccwienk-0.2.5.dist-info/LICENSE
containerregistry_ccwienk-0.2.5.dist-info/METADATA
containerregistry_ccwienk-0.2.5.dist-info/WHEEL
containerregistry_ccwienk-0.2.5.dist-info/top_level.txt
containerregistry_ccwienk-0.2.5.dist-info/RECORD
