Metadata-Version: 2.1
Name: containerregistry-ccwienk
Version: 0.2.5
Summary: a library and tools for interacting with container registries
Home-page: https://github.com/ccwienk/containerregistry
Author: Christian Cwienk
Author-email: Christian.Cwienk@sap.com
License: UNKNOWN
Platform: UNKNOWN
Classifier: Programming Language :: Python :: 3
Classifier: License :: OSI Approved :: Apache Software License
Classifier: Operating System :: OS Independent
Requires-Dist: futures (>=3.1.1)
Requires-Dist: httplib2 (>=0.11.3)
Requires-Dist: oauth2client (>=4.0)
Requires-Dist: six (>=1.9)
